{
  "version": 8,
  "name": "UmiLog Underwater",
  "sources": {
    "esri-ocean": {
      "type": "raster",
      "tiles": [
        "https://services.arcgisonline.com/arcgis/rest/services/Ocean/World_Ocean_Base/MapServer/tile/{z}/{y}/{x}"
      ],
      "tileSize": 256,
      "minzoom": 0,
      "maxzoom": 13,
      "attribution": "Esri, GEBCO, NOAA, National Geographic"
    },
    "carto-voyager": {
      "type": "raster",
      "tiles": [
        "https://basemaps.cartocdn.com/rastertiles/voyager_nolabels/{z}/{x}/{y}@2x.png"
      ],
      "tileSize": 512,
      "minzoom": 0,
      "maxzoom": 18,
      "attribution": "© OpenStreetMap contributors, © CARTO"
    }
  },
  "layers": [
    {
      "id": "background",
      "type": "background",
      "paint": {
        "background-color": "#08141A"
      }
    },
    {
      "id": "ocean-base",
      "type": "raster",
      "source": "esri-ocean",
      "minzoom": 0,
      "maxzoom": 13,
      "paint": {
        "raster-opacity": 1.0,
        "raster-brightness-min": 0.05,
        "raster-brightness-max": 0.6,
        "raster-contrast": 0.35,
        "raster-saturation": -0.2
      }
    },
    {
      "id": "carto-base",
      "type": "raster",
      "source": "carto-voyager",
      "minzoom": 0,
      "maxzoom": 18,
      "paint": {
        "raster-opacity": 0.85,
        "raster-brightness-min": 0.0,
        "raster-brightness-max": 0.35,
        "raster-contrast": 0.3,
        "raster-saturation": -0.1,
        "raster-hue-rotate": 200
      }
    }
  ]
}
